berna_tjgo_diacde_lib/__init__.py
berna_tjgo_diacde_lib/src/__init__.py
berna_tjgo_diacde_lib/src/preprocessing/__init__.py
berna_tjgo_diacde_lib/src/preprocessing/_methods.py
berna_tjgo_diacde_lib/src/preprocessing/preprocessing.py
berna_tjgo_diacde_lib/src/similarity/__init__.py
berna_tjgo_diacde_lib/src/similarity/berna.py
berna_tjgo_diacde_lib_old/__init__.py
berna_tjgo_diacde_lib_old/teste.py
tests/__init__.py
tests/teste_geral.py
tests/teste_prep.py
berna_tjgo_diacde_lib-1.1.1.dist-info/METADATA
berna_tjgo_diacde_lib-1.1.1.dist-info/WHEEL
berna_tjgo_diacde_lib-1.1.1.dist-info/top_level.txt
berna_tjgo_diacde_lib-1.1.1.dist-info/RECORD
