Metadata-Version: 2.1
Name: berna_tjgo_diacde_lib
Version: 1.1.1
Home-page: https://github.com/TJGO-DIACDE/berna_tjgo_diacde_lib
Author: DIACDE - TJGO
License: Attribution-NonCommercial-ShareAlike
Requires-Python: >=3.9.4
